{
    "stories": [
        {
            "id": 1,
            "title": "Little hedgehog's new hairstyle 小刺猬的新发型"
        },
        {
            "id": 2,
            "title": "The most intelligent birds 鸟中诸葛"
        },
        {
            "id": 3,
            "title": "Hong and Dan 红红和丹丹"
        },
        {
            "id": 4,
            "title": "The gift 礼物"
        },
        {
            "id": 5,
            "title": "My brother turned into a red guy 哥哥变成了“红人”"
        },
        {
            "id": 6,
            "title": "Small park 小公园"
        },
        {
            "id": 7,
            "title": "Old people 欢迎圣诞老人"
        }
    ]
}
